megania/__init__.py
megania/megan.py
megania/tensor.py
megania/tokenizer.py
megania/transformer.py
megania-0.0.1.dist-info/METADATA
megania-0.0.1.dist-info/WHEEL
megania-0.0.1.dist-info/top_level.txt
megania-0.0.1.dist-info/RECORD
