Metadata-Version: 2.4
Name: megania
Version: 0.0.1
Summary: IA Megan con tensores y tokenizador básico sin dependencias
Author: Tu Nombre
Author-email: tu@email.com
License: MIT
Keywords: IA,tensores,tokenizador,transformer
Classifier: Programming Language :: Python :: 3
Classifier: License :: OSI Approved :: MIT License
Classifier: Operating System :: OS Independent
Requires-Python: >=3.8
